pyjuicenet/__init__.py
python_juicenet-1.1.0.dist-info/LICENSE
python_juicenet-1.1.0.dist-info/METADATA
python_juicenet-1.1.0.dist-info/WHEEL
python_juicenet-1.1.0.dist-info/top_level.txt
python_juicenet-1.1.0.dist-info/zip-safe
python_juicenet-1.1.0.dist-info/RECORD
