Metadata-Version: 2.1
Name: python-juicenet
Version: 1.1.0
Summary: Read and control Juicenet/Juicepoint/Juicebox based EVSE devices
Home-page: http://github.com/jesserockz/python-juicenet
Author: @jesserockz
License: MIT
Platform: UNKNOWN
License-File: LICENSE
Requires-Dist: aiohttp
